firewheel_repo_dns/configure_bind/MANIFEST
firewheel_repo_dns/configure_bind/README.rst
firewheel_repo_dns/configure_bind/plugin.py
firewheel_repo_dns/configure_bind/vm_resources/configure_bind_agent.py
firewheel_repo_dns/dns_objects/MANIFEST
firewheel_repo_dns/dns_objects/README.rst
firewheel_repo_dns/dns_objects/model_component_objects.py
firewheel_repo_dns/dns_objects/INSTALL/tasks.yml
firewheel_repo_dns/dns_objects/INSTALL/vars.yml
firewheel_repo_dns/dns_objects/vm_resources/.gitkeep
firewheel_repo_dns/insert_dns/MANIFEST
firewheel_repo_dns/insert_dns/README.rst
firewheel_repo_dns/insert_records/MANIFEST
firewheel_repo_dns/insert_records/README.rst
firewheel_repo_dns/insert_records/plugin.py
firewheel_repo_dns/populate_zones/MANIFEST
firewheel_repo_dns/populate_zones/README.rst
firewheel_repo_dns/populate_zones/plugin.py
firewheel_repo_dns/set_nameservers/MANIFEST
firewheel_repo_dns/set_nameservers/README.rst
firewheel_repo_dns/set_nameservers/plugin.py
firewheel_repo_dns/set_nameservers/vm_resources/set_nameservers_agent.py
firewheel_repo_dns-3.0.0.dist-info/licenses/LICENSE
firewheel_repo_dns-3.0.0.dist-info/METADATA
firewheel_repo_dns-3.0.0.dist-info/WHEEL
firewheel_repo_dns-3.0.0.dist-info/entry_points.txt
firewheel_repo_dns-3.0.0.dist-info/top_level.txt
firewheel_repo_dns-3.0.0.dist-info/RECORD
